{
  "$schema": "https://developer.microsoft.com/json-schemas/fabric/item/report/definition/visualContainer/2.2.0/schema.json",
  "name": "4a7216259985e2715647",
  "position": {
    "x": 30.212598425196852,
    "y": 13.847440944881889,
    "z": 0,
    "height": 40.283464566929133,
    "width": 1085.1358267716535
  },
  "visual": {
    "visualType": "textbox",
    "objects": {
      "general": [
        {
          "properties": {
            "paragraphs": [
              {
                "textRuns": [
                  {
                    "value": "STORE SALES REPORT",
                    "textStyle": {
                      "fontFamily": "Segoe (Bold)",
                      "fontSize": "15pt"
                    }
                  },
                  {
                    "value": " ",
                    "textStyle": {
                      "fontFamily": "Segoe (Bold)",
                      "fontSize": "18pt"
                    }
                  },
                  {
                    "value": "Detailed Info",
                    "textStyle": {
                      "fontFamily": "Segoe UI"
                    }
                  }
                ]
              }
            ]
          }
        }
      ]
    },
    "visualContainerObjects": {
      "title": [
        {
          "properties": {
            "show": {
              "expr": {
                "Literal": {
                  "Value": "false"
                }
              }
            },
            "text": {
              "expr": {
                "Literal": {
                  "Value": "'SALES AND MARKETING'"
                }
              }
            },
            "fontSize": {
              "expr": {
                "Literal": {
                  "Value": "'17'"
                }
              }
            },
            "fontFamily": {
              "expr": {
                "Literal": {
                  "Value": "'''Segoe UI Bold'', wf_segoe-ui_bold, helvetica, arial, sans-serif'"
                }
              }
            },
            "fontColor": {
              "solid": {
                "color": {
                  "expr": {
                    "ThemeDataColor": {
                      "ColorId": 1,
                      "Percent": 0
                    }
                  }
                }
              }
            }
          }
        }
      ],
      "background": [
        {
          "properties": {
            "show": {
              "expr": {
                "Literal": {
                  "Value": "true"
                }
              }
            },
            "transparency": {
              "expr": {
                "Literal": {
                  "Value": "0D"
                }
              }
            }
          }
        }
      ]
    }
  }
}